autoops/__init__.py
autoops/analyzer.py
autoops/cli.py
autoops/config.py
autoops/github_client.py
autoops/issue_creator.py
autoops/poller.py
autoops/state.py
autoops-0.2.5.dist-info/licenses/LICENSE
autoops-0.2.5.dist-info/METADATA
autoops-0.2.5.dist-info/WHEEL
autoops-0.2.5.dist-info/entry_points.txt
autoops-0.2.5.dist-info/top_level.txt
autoops-0.2.5.dist-info/RECORD
