Metadata-Version: 2.4
Name: autoops
Version: 0.2.5
Summary: AutoOps: Fully automatic AI DevOps agent with polling mode (no webhooks required)
Author: AutoOps
License-File: LICENSE
Requires-Dist: typer
Requires-Dist: requests
Requires-Dist: python-dotenv
Dynamic: license-file
